streamlined_custom_component/__init__.py
streamlined_custom_component/component.py
streamlit_custom_component-0.2.dist-info/METADATA
streamlit_custom_component-0.2.dist-info/WHEEL
streamlit_custom_component-0.2.dist-info/top_level.txt
streamlit_custom_component-0.2.dist-info/RECORD
